Workbook
Name ABRIL: #REF!
Name AFP: #REF!
Name afps: #REF!
Name Alquiler: ADM_ESC!$C$9
Name Año: '[1]tabla dinamica'!$B$2:$B$25
Name AREA1: '[2]Base de Datos'!$B$3:$B$6
Name AREA2: '[2]Base de Datos'!$D$3:$D$6
Name AREAS: #REF!
Name BANCO: [3]banco!#REF!
Name BASE: #REF!
Name base1: #REF!
Name base2: #REF!
Name BASE3: #REF!
Name base4: '[4]FUNC DE BASE DE DATOS'!$A$1:$H$33
Name baseCliente: #REF!
Name BASER2: #REF!
Name BONO: #REF!
Name BUSCAR: #REF!
Name Campeonatos_Ganados: #REF!
Name CIUDAD: #REF!
Name Cliente: '[1]tabla dinamica'!$A$2:$A$25
Name Clientes: #REF!
Name Comuna: #REF!
Name CONDICION: #REF!
Name criterio: #REF!
Name Cruz_Blanca: '[5]Hoja1 (4)'!#REF!
Name CruzBlanca: #REF!
Name datos: #REF!
Name dd: '[6]tabla (3)'!$A$1:$D$5
Name ddd: #REF!
Name dddrr: #REF!
Name DEPTO: #REF!
Name DESC._AFP: #REF!
Name DESC._ISAPRE: #REF!
Name DIRECCION: #REF!
Name dolar: '[1]tabla dinamica'!$B$27
Name DPTO.: #REF!
Name fdg: #REF!
Name final: #REF!
Name Fonasa: #REF!
Name funciones: #REF!
Name GONZALEZ: #REF!
Name Habitat: #REF!
Name hh: #REF!
Name hhh: #REF!
Name ISAPRE: #REF!
Name isapres: #REF!
Name jjjj: #REF!
Name Marca: #REF!
Name Marketing: ADM_ESC!$C$11
Name Martes_20_05_2008: [7]Sheet1!#REF!
Name MAYO: '[8]Hoja2 (2)'!$A$9:$K$13
Name Mes: '[1]tabla dinamica'!$C$2:$C$25
Name Monto: '[1]tabla dinamica'!$D$2:$D$25
Name Monto_Pagado: #REF!
Name MONTOS: #REF!
Name Mora: #REF!
Name N__de_cajas: #REF!
Name N__de_personal: #REF!
Name NativeTimeline_FECHA: #N/A

Sheet PREGUNTAS
A1: PRACTICA FINAL
A3: LIC. ALESSANDRO PASCUA CAMARENA
B6: PREGUNTAS | D6: 0.5 PTS c/u
A8: 1 | B8: CUAL ES LA DIFERENCIA ENTRE SELECCIONAR DATOS EN BASE A UN RANGO Y EN BASE A UN FORMATO TABLA (ESPECIFICAR LA VENTAJA DE LA TABLA)
B9: La diferencia es que el rango es solamente un conjunto de celdas estáticas seleccionadas, mientras que el formato de Tabla convierte a ese rango de celdas en un objeto estructurado y dinámico, y la ventaja de la tabla es que proveé dinamismo a la hora de ingresar más datos, ya que se podrá reflejar en, por ejemplo, un gráfico al solamente Actualizar.
A10: 2 | B10: ES POSIBLE CREAR TABLA DINAMICA SIN GRAFICO DINAMICO? Y CREAR GRAFICO DINAMICO SIN TABLA DINAMICA?
B11: Sí es posible crear una tabla dinámica sin gráfico dinámico, mas no es posible crear un gráfico dinámico sin tabla dinámica

Sheet BASE1
A9: FECHA | B9: FACTURA | C9: RUC | D9: CLIENTES | E9: REGION | F9: LINEA | G9: REPRESENTANTE | H9: IMPORTE | I9: IGV | J9: TOTAL
A10: 43831 | B10: 001-10251 | C10: 20160641810 | D10: LABORATORIOS BAGO DEL PERU S.A. | E10: OESTE | F10: BLANCA | G10: Janet Lopez | H10: 7551 | I10: 1359.18 | J10: 8910.18
A11: 43832 | B11: 001-10252 | C11: 20390473142 | D11: DUKE ENERGY INTERNATIONAL PERU INVESTMEN | E11: NORTE | F11: BLANCA | G11: Jorge Bardales | H11: 5000 | I11: 900 | J11: 5900
A12: 43833 | B12: 001-10253 | C12: 20100128994 | D12: AGA S A | E12: CENTRO | F12: BLANCA | G12: Margarita Palacios | H12: 1119.9 | I12: 201.582 | J12: 1321.482
A13: 43834 | B13: 001-10254 | C13: 20100562848 | D13: COMPANIA UNIVERSAL TEXTIL S.A. | E13: ESTE | F13: BLANCA | G13: Jorge Bardales | H13: 96913 | I13: 17444.34 | J13: 114357.34
A14: 43835 | B14: 001-10255 | C14: 20377444257 | D14: NEGOCIACIONES JFK S.A.C. | E14: NORTE | F14: BLANCA | G14: Andres Flores | H14: 1176 | I14: 211.68 | J14: 1387.68
A15: 43836 | B15: 001-10256 | C15: 20266352337 | D15: PRODUCTOS TISSUE DEL PERU S.A. O PROTISA | E15: OESTE | F15: COMPUTO | G15: Jorge Bardales | H15: 1101.2 | I15: 198.216 | J15: 1299.416
A16: 43837 | B16: 001-10257 | C16: 20258886420 | D16: ROSEN PERU S.A. | E16: SUR | F16: COMPUTO | G16: Jorge Bardales | H16: 5023 | I16: 904.14 | J16: 5927.14
A17: 43838 | B17: 001-10258 | C17: 20100051240 | D17: FCA PERUANA ETERNIT S A | E17: NORTE | F17: BLANCA | G17: Andres Flores | H17: 613.2 | I17: 110.376 | J17: 723.576
A18: 43839 | B18: 001-10259 | C18: 20418141281 | D18: CIPA S.A. | E18: ESTE | F18: BLANCA | G18: Jorge Bardales | H18: 2169 | I18: 390.42 | J18: 2559.42
A19: 43840 | B19: 001-10260 | C19: 20122263143 | D19: FULL FISH SAC | E19: NORTE | F19: BLANCA | G19: Jorge Bardales | H19: 2500.9 | I19: 450.162 | J19: 2951.062
A20: 43841 | B20: 001-10261 | C20: 20101362702 | D20: CONFECCIONES TEXTIMAX S A | E20: ESTE | F20: COMPUTO | G20: Jorge Bardales | H20: 500 | I20: 90 | J20: 590
A21: 43842 | B21: 001-10262 | C21: 20330011930 | D21: CISCO SYSTEMS PERU S.A | E21: ESTE | F21: COMPUTO | G21: Jorge Bardales | H21: 268.8 | I21: 48.384 | J21: 317.184
... A258: 44079 | B258: 001-10438 | C258: 20100067596 | D258: FABRICA DE CUBIERTOS SAC | E258: ESTE | F258: BLANCA | G258: Margarita Palacios | H258: 5218 | I258: 939.24 | J258: 6157.24

Sheet TD1
B1: 3 pts | D1: -0.5pts cada error
A3: 1 | B3: De la hoja BASE1 crear un tabla dinamica en base a la selección del cuadro de datos, colocarla en esta hoja y renombrar la hoja como TD1, la tabla dinamica debe llamarse como la hoja
A4: 2 | B4: Colocar en el area de campos region en filas, representante en columnas, total en valores
A5: 3 | B5: Agregar campo calculado a la tabla dinamica que sea Tdolares que refleje su valor con un tipo de cambio de 3.15 (solo trabajar Tdolares en valores, ya no Total ) | K5: SE DIVIDE EL TC
A6: 4 | B6: Agregar diseño de tabla y colocar a los montos formato moneda dolares
A7: 5 | B7: Filtrar en solo region norte,sur, y centro; y tambien filtrar a los representantes solo a las mujeres (UTILIZANDO SEGMENTACION DE DATOS con diseño)
A8: 6 | B8: Agregar grafico dinamico de Tipo Linea y agregar estilo cualquiera menos el original y quitar los botones de filtrado
A9: 7 | B9: Insertar segmentacion de escala de tiempo
B11: (Crear aquí mismo la tabla dinamica)
B12: Suma de Tdolares | C12: Etiquetas de columna
B13: Etiquetas de fila | C13: Janet Lopez | D13: Laura Cabellero | E13: Margarita Palacios | F13: Total general
B14: CENTRO | C14: 10675.447 | D14: 0 | E14: 21697.058 | F14: 32372.505
B15: NORTE | C15: 111771.71 | D15: 37793.564 | E15: 0 | F15: 149565.28
B16: SUR | C16: 26522.096 | D16: 10954.78 | E16: 0 | F16: 37476.876
B17: Total general | C17: 148969.26 | D17: 48748.343 | E17: 21697.058 | F17: 219414.66

Sheet TD2
B1: 3 pts | D1: -0.5pts cada error
A3: 1 | B3: De la hoja BASE1 crear un tabla dinamica en base a la tabla(debes convertir el rango en tabla) , colocarla en esta hoja y renombrar la hoja como TD2, la tabla dinamica debe llamarse como la hoja
A4: 2 | B4: Colocar en area de campos region en columnas, representante en filas y debajo de representantes fecha en meses, total en valores. Y linea en filtros
A5: 3 | B5: Agregar diseño de tabla y colocar a los montos formato moneda en soles
A6: 4 | B6: Filtrar en solo region este y oeste, y tambien filtrar a los representantes solo a los hombres (UTILIZANDO SEGMENTACION DE DATOS)
A7: 5 | B7: Agregar grafico dinamico de tipo columnas y cambiar el estilo al grafico (cualquiera menos el original) y quitar los botones de filtrado
A8: 6 | B8: Insertar escala de tiempo y mostrar desde enero hasta junio
A9: 7 | B9: Finalmente mostrar paginas de filtros de informes (para que según el campo que este en filtros se creen hojas de cada uno) las hojas se deben llamar como su filtro
B10: LINEA | C10: (Todas)
B11: (Crear aquí mismo la tabla dinamica)
B12: Suma de TOTAL | C12: Etiquetas de columna
B13: Etiquetas de fila | C13: ESTE | D13: OESTE | E13: Total general
B14: Andres Flores | C14: 53183.815 | D14: 4261.983 | E14: 57445.798
B15: Ene | C15: 6035.2044 | E15: 6035.2044
B16: Feb | C16: 3864.6534 | D16: 1038.99 | E16: 4903.6434
B17: Mar | C17: 5649.84 | D17: 1768.053 | E17: 7417.893
B18: May | C18: 18817.059 | D18: 727.47 | E18: 19544.529
B19: Jun | C19: 18817.059 | D19: 727.47 | E19: 19544.529
B20: Jorge Bardales | C20: 129555.52 | D20: 5846.4988 | E20: 135402.01
B21: Ene | C21: 125776.92 | D21: 1299.416 | E21: 127076.34
B22: Mar | C22: 3778.596 | E22: 3778.596
B23: Abr | D23: 3670.9328 | E23: 3670.9328
B24: Jun | D24: 876.15 | E24: 876.15
B25: Total general | C25: 182739.33 | D25: 10108.482 | E25: 192847.81

Sheet BLANCA
A1: LINEA | B1: BLANCA
A3: Suma de TOTAL | B3: Etiquetas de columna
A4: Etiquetas de fila | B4: ESTE | C4: OESTE | D4: Total general
A5: Andres Flores | B5: 8946.996 | C5: 4261.983 | D5: 13208.979
A6: Ene | B6: 3899.4044 | D6: 3899.4044
A7: Feb | C7: 1038.99 | D7: 1038.99
A8: Mar | C8: 1768.053 | D8: 1768.053
A9: May | B9: 2523.7958 | C9: 727.47 | D9: 3251.2658
A10: Jun | B10: 2523.7958 | C10: 727.47 | D10: 3251.2658
A11: Jorge Bardales | B11: 125386.72 | C11: 2794.7828 | D11: 128181.5
A12: Ene | B12: 123287.26 | D12: 123287.26
A13: Mar | B13: 2099.456 | D13: 2099.456
A14: Abr | C14: 2794.7828 | D14: 2794.7828
A15: Total general | B15: 134333.71 | C15: 7056.7658 | D15: 141390.48

Sheet COMPUTO
A1: LINEA | B1: COMPUTO
A3: Suma de TOTAL | B3: Etiquetas de columna
A4: Etiquetas de fila | B4: ESTE | C4: OESTE | D4: Total general
A5: Andres Flores | B5: 44236.819 | D5: 44236.819
A6: Ene | B6: 2135.8 | D6: 2135.8
A7: Feb | B7: 3864.6534 | D7: 3864.6534
A8: Mar | B8: 5649.84 | D8: 5649.84
A9: May | B9: 16293.263 | D9: 16293.263
A10: Jun | B10: 16293.263 | D10: 16293.263
A11: Jorge Bardales | B11: 4168.7984 | C11: 3051.716 | D11: 7220.5144
A12: Ene | B12: 2489.6584 | C12: 1299.416 | D12: 3789.0744
A13: Mar | B13: 1679.14 | D13: 1679.14
A14: Abr | C14: 876.15 | D14: 876.15
A15: Jun | C15: 876.15 | D15: 876.15
A16: Total general | B16: 48405.618 | C16: 3051.716 | D16: 51457.334

Sheet TABLA_CONSOL
B2: Insertar tabla dinamica de consolidacion multiple en esta hoja lineas abajo respecto a las hojas Mujeres y Hombres , a la tabla agregarle un diseño identico | N2: 1 pt
B3: Revisar que en la parte de filtros LOS ELEMENTOS SEAN EL TIPO DE SEXO (MASCULINO Y FEMENINO) | J3: Utiliza el asistente para tablas y graficos dinamicos)
K4: SEXO | L4: (Todas)
K6: Suma de Valor
K7: REPRESENTANTE | L7: IGV | M7: IMPORTE | N7: TOTAL | O7: Total general
K8: Andres Flores | L8: 1882.818 | M8: 10460.1 | N8: 12342.918 | O8: 24685.836
K9: Janet Lopez | L9: 1456.848 | M9: 8093.6 | N9: 9550.448 | O9: 19100.896
K10: Jorge Bardales | L10: 20377.278 | M10: 113207.1 | N10: 133584.38 | O10: 267168.76
K11: Laura Cabellero | L11: 707.3748 | M11: 3929.86 | N11: 4637.2348 | O11: 9274.4696
K12: Margarita Palacios | L12: 1410.2838 | M12: 7834.91 | N12: 9245.1938 | O12: 18490.388
K13: Total general | L13: 25834.603 | M13: 143525.57 | N13: 169360.17 | O13: 338720.35

Sheet MUJERES
A4: REPRESENTANTE | B4: IMPORTE | C4: IGV | D4: TOTAL
A5: Janet Lopez | B5: 268.8 | C5: 48.384 | D5: 317.184
A6: Janet Lopez | B6: 1614.8 | C6: 290.664 | D6: 1905.464
A7: Janet Lopez | B7: 1810 | C7: 325.8 | D7: 2135.8
A8: Janet Lopez | B8: 88.5 | C8: 15.93 | D8: 104.43
A9: Margarita Palacios | B9: 2436.18 | C9: 438.5124 | D9: 2874.6924
A10: Margarita Palacios | B10: 5398.73 | C10: 971.7714 | D10: 6370.5014
A11: Janet Lopez | B11: 136.3 | C11: 24.534 | D11: 160.834
A12: Janet Lopez | B12: 1549.6 | C12: 278.928 | D12: 1828.528
A13: Laura Cabellero | B13: 950 | C13: 171 | D13: 1121
A14: Janet Lopez | B14: 403.2 | C14: 72.576 | D14: 475.776
A15: Laura Cabellero | B15: 1689.78 | C15: 304.1604 | D15: 1993.9404
A16: Laura Cabellero | B16: 103.2 | C16: 18.576 | D16: 121.776
... A19: Laura Cabellero | B19: 287.88 | C19: 51.8184 | D19: 339.6984

Sheet HOMBRES
A5: REPRESENTANTE | B5: IMPORTE | C5: IGV | D5: TOTAL
A6: Andres Flores | B6: 7551 | C6: 1359.18 | D6: 8910.18
A7: Jorge Bardales | B7: 5000 | C7: 900 | D7: 5900
A8: Andres Flores | B8: 1119.9 | C8: 201.582 | D8: 1321.482
A9: Jorge Bardales | B9: 96913 | C9: 17444.34 | D9: 114357.34
A10: Andres Flores | B10: 1176 | C10: 211.68 | D10: 1387.68
A11: Jorge Bardales | B11: 1101.2 | C11: 198.216 | D11: 1299.416
A12: Jorge Bardales | B12: 5023 | C12: 904.14 | D12: 5927.14
A13: Andres Flores | B13: 613.2 | C13: 110.376 | D13: 723.576
A14: Jorge Bardales | B14: 2169 | C14: 390.42 | D14: 2559.42
A15: Jorge Bardales | B15: 2500.9 | C15: 450.162 | D15: 2951.062
A16: Jorge Bardales | B16: 500 | C16: 90 | D16: 590

Sheet CONSOL
A1: PRACTICA 4 MODULO AVANZADO1
A3: ECON. ALESSANDRO PASCUA CAMARENA
A6: 1 | B6: Crear un cuadro lineas abajo consolidando la informacion de estos 3 cuadros correctamente | I6: 0.5 PTS
A7: 2 | B7: Crear un cuadro en otra hoja consolidando la informacion de estos 3 cuadros correctamente con vinculos | I7: 0.5 PTS
B9: Producto | C9: Comision | D9: Ventas | G9: Producto | H9: Ventas | I9: Comision | L9: Producto | M9: Ventas | N9: Comision
B10: Diccionarios | C10: =+D10*10% -> 5.4 | D10: 54 | G10: Enciclopedias | H10: 54 | I10: =+H10*10% -> 5.4 | L10: Enciclopedias | M10: 54 | N10: =+M10*10% -> 5.4
B11: Atlas | C11: 5 | D11: 60 | G11: Atlas | H11: 40 | I11: =+H11*10% -> 4 | L11: Atlas | M11: 40 | N11: =+M11*10% -> 4
B12: Enciclopedias | C12: 6 | D12: 70 | G12: Diccionarios | H12: 65 | I12: =+H12*10% -> 6.5 | L12: Diccionarios | M12: 65 | N12: =+M12*10% -> 6.5
B13: Periodicos | C13: 2 | D13: 50 | G13: Periodicos | H13: 30 | I13: =+H13*10% -> 3 | L13: Periodicos | M13: 30 | N13: =+M13*10% -> 3
E17: Producto | F17: Comision | G17: Ventas
E18: Diccionarios | F18: 18.4 | G18: 184
E19: Atlas | F19: 13 | G19: 140
E20: Enciclopedias | F20: 16.8 | G20: 178
E21: Periodicos | F21: 8 | G21: 110

Sheet CONSOL HOJA
C6: Productos | E6: Comision | F6: Ventas
D7: Practica_Final | E7: =CONSOL!$C$10 -> 5.4 | F7: =CONSOL!$D$10 -> 54
D8: Practica_Final | E8: =CONSOL!$I$12 -> 6.5 | F8: =CONSOL!$H$12 -> 65
D9: Practica_Final | E9: =CONSOL!$N$12 -> 6.5 | F9: =CONSOL!$M$12 -> 65
C10: Diccionarios | E10: =SUM(E7:E9) -> 18.4 | F10: =SUM(F7:F9) -> 184
D11: Practica_Final | E11: =CONSOL!$C$11 -> 5 | F11: =CONSOL!$D$11 -> 60
D12: Practica_Final | E12: =CONSOL!$I$11 -> 4 | F12: =CONSOL!$H$11 -> 40
D13: Practica_Final | E13: =CONSOL!$N$11 -> 4 | F13: =CONSOL!$M$11 -> 40
C14: Atlas | E14: =SUM(E11:E13) -> 13 | F14: =SUM(F11:F13) -> 140
D15: Practica_Final | E15: =CONSOL!$C$12 -> 6 | F15: =CONSOL!$D$12 -> 70
D16: Practica_Final | E16: =CONSOL!$I$10 -> 5.4 | F16: =CONSOL!$H$10 -> 54
D17: Practica_Final | E17: =CONSOL!$N$10 -> 5.4 | F17: =CONSOL!$M$10 -> 54
C18: Enciclopedias | E18: =SUM(E15:E17) -> 16.8 | F18: =SUM(F15:F17) -> 178
D19: Practica_Final | E19: =CONSOL!$C$13 -> 2 | F19: =CONSOL!$D$13 -> 50
D20: Practica_Final | E20: =CONSOL!$I$13 -> 3 | F20: =CONSOL!$H$13 -> 30
D21: Practica_Final | E21: =CONSOL!$N$13 -> 3 | F21: =CONSOL!$M$13 -> 30
C22: Periodicos | E22: =SUM(E19:E21) -> 8 | F22: =SUM(F19:F21) -> 110

Sheet FORM_COND
A1: PRACTICA MODULO AVANZADO1
A3: ECON. ALESSANDRO PASCUA CAMARENA
A5: Insertar formato tabla, centrar las celdas y poner formato moneda si corresponde
A7: Apellido Paterno | B7: Nombre | C7: Distrito | D7: Ingreso 1 | E7: Ingreso 2 | F7: Ingreso 3 | G7: Departamento | J7: Ingreso 1 | N7: 0.5 pts
A8: OLIVARES | B8: Luis Alberto | C8: Santiago de Surco | D8: 3145.5 | E8: 3495 | F8: 6990.1 | G8: Finanzas | J8: Color amarillo+Relleno plomo los 5 montos mas altos
A9: SALAZAR | B9: Patricio Ian | C9: La Molina | D9: 3141.9 | E9: 3491 | F9: 6982.1 | G9: Contabilidad | J9: Color azul+relleno rosa 3 montos mas bajos
A10: GEREDA | B10: Gianfranco | C10: Santiago de Surco | D10: 3130.2 | E10: 3478 | F10: 6956.1 | G10: Contabilidad
A11: ESPINOSA | B11: Fernando Alfredo | C11: La Punta | D11: 3128.4 | E11: 3476 | F11: 6952.1 | G11: Marketing | J11: Ingreso 2 | N11: 0.5 pts
A12: LA ROSA | B12: Javier Antonio | C12: La Molina | D12: 3120.3 | E12: 3467 | F12: 6934.1 | G12: Marketing | J12: ICONOS | L12: Barra de Datos=VERDE
A13: BENAVIDES | B13: Augusto Felipe | C13: San Miguel | D13: 3105.9 | E13: 3451 | F13: 6902.1 | G13: Contabilidad | J13: < 2,000 | L13: Sueldo Maximo | M13: 5000
A14: DEDIOS | B14: Eduardo Rodrigo | C14: San Isidro | D14: 3081.6 | E14: 3424 | F14: 6848.1 | G14: Marketing | J14: >= 2,000 < 3,000
A15: BENAVENTE | B15: Augusto | C15: Magdalena | D15: 3078.9 | E15: 3421 | F15: 6842.1 | G15: Marketing | J15: >= 3,000
A16: BARREDA | B16: Andrés Vladimir | C16: Santiago de Surco | D16: 3066.3 | E16: 3407 | F16: 6814.1 | G16: Contabilidad
A17: BURGOS | B17: Carlos Alberto | C17: Magdalena | D17: 3061.8 | E17: 3402 | F17: 6804.1 | G17: Producción | J17: Ingreso 3 | N17: 0.5 pts
A18: ELIAS | B18: Fernando | C18: Lince | D18: 3061.8 | E18: 3402 | F18: 6804.1 | G18: Producción | J18: Resaltar de color amarillo los montos superiores al promedio
A19: MOSCOL | B19: Juan Manuel | C19: Ate-Vitarte | D19: 3044.7 | E19: 3383 | F19: 6766.1 | G19: Producción | J19: Resaltar de color morado los montos inferiores al promedio
A20: EGUILUZ | B20: Fernando | C20: San Borja | D20: 3039.3 | E20: 3377 | F20: 6754.1 | G20: Contabilidad
A21: MURDOCH | B21: Juan Pablo | C21: San Borja | D21: 3022.2 | E21: 3358 | F21: 6716.1 | G21: Finanzas | J21: Departamento | N21: 0.5 pts
A22: LESCANO | B22: Jorge Andrés | C22: Santiago de Surco | D22: 3018.6 | E22: 3354 | F22: 6708.1 | G22: Contabilidad | J22: RELLENO:
A23: MARTINEZ | B23: José Francisco | C23: Miraflores | D23: 3003.3 | E23: 3337 | F23: 6674.1 | G23: Contabilidad | J23: Departamento | K23: Color
A24: TEPLY | B24: Ricardo | C24: Miraflores | D24: 2999.7 | E24: 3333 | F24: 6666.1 | G24: Marketing | J24: Contabilidad
A25: NICOLINI | B25: Julio | C25: San Isidro | D25: 2994.3 | E25: 3327 | F25: 6654.1 | G25: Producción | J25: Finanzas
A26: ESCULIES | B26: Fernando | C26: La Molina | D26: 2992.5 | E26: 3325 | F26: 6650.1 | G26: Producción | J26: Producción
A27: ROSHOLT | B27: Nicolás Alessandro | C27: La Molina | D27: 2991.6 | E27: 3324 | F27: 6648.1 | G27: Finanzas | J27: Marketing
A28: ARRIOLA | B28: Alvaro | C28: San Isidro | D28: 2983.5 | E28: 3315 | F28: 6630.1 | G28: Producción
A29: GRISOLLE | B29: Gonzalo Elehin | C29: Lince | D29: 2979 | E29: 3310 | F29: 6620.1 | G29: Contabilidad
A30: DE LOS HEROS | B30: Eduardo | C30: La Molina | D30: 2975.4 | E30: 3306 | F30: 6612.1 | G30: Contabilidad
A31: FRANCO DE SOUZA | B31: Franco | C31: La Molina | D31: 2948.4 | E31: 3276 | F31: 6552.1 | G31: Producción
A32: DANJOY | B32: Diego José | C32: Santiago de Surco | D32: 2946.6 | E32: 3274 | F32: 6548.1 | G32: Finanzas
A33: TABOADA | B33: Ricardo | C33: San Borja | D33: 2943.9 | E33: 3271 | F33: 6542.1 | G33: Finanzas
A34: ARIAS | B34: Alvaro | C34: La Molina | D34: 2940.3 | E34: 3267 | F34: 6534.1 | G34: Finanzas
A35: REATEGUI | B35: Martín Alonso | C35: Santiago de Surco | D35: 2936.7 | E35: 3263 | F35: 6526.1 | G35: Finanzas
A36: MENENDEZ | B36: José Ricardo | C36: Miraflores | D36: 2932.2 | E36: 3258 | F36: 6516.1 | G36: Finanzas
A37: GALLASTEGUI | B37: Gabriel | C37: San Borja | D37: 2918.7 | E37: 3243 | F37: 6486.1 | G37: Finanzas
A38: CHAVEZ | B38: Diego Alonso | C38: La Molina | D38: 2917.8 | E38: 3242 | F38: 6484.1 | G38: Producción
A39: POMAREDA | B39: Marco Antonio | C39: Miraflores | D39: 2917.8 | E39: 3242 | F39: 6484.1 | G39: Marketing
... A306: OLCESE | B306: Luis | C306: Miraflores | D306: 907.2 | E306: 1008 | F306: 2016.1 | G306: Contabilidad

Sheet FORM_COND_FORM
B3: Código | C3: Vehículo | D3: Departamento | E3: Zona | F3: Cantidad | G3: Monto | I3: *Crear un formato condicional que dependa de la lista desplegable de Zona | O3: 1 pt
B4: HP-101 | C4: Automóvil | D4: Amazonas | E4: Norte | F4: 256 | G4: 17920 | I4: *Seleccionar la fila de la tabla en caso se cumpla el caso
B5: HP-090 | C5: Omnibus | D5: Ancash | E5: Norte | F5: 45 | G5: 3150 | I5: (Que no se resalte solo la celda sino la fila entera) --> Utiliza el formato condicional Formula
B6: HP-101 | C6: Automóvil | D6: Apurimac | E6: Sur | F6: 479 | G6: 33530
B7: HP-115 | C7: Camioneta | D7: Arequipa | E7: Sur | F7: 394 | G7: 27580
B8: HP-130 | C8: Camión | D8: Ayacucho | E8: Sur | F8: 306 | G8: 21420 | I8: Sur
B9: HP-090 | C9: Omnibus | D9: Cajamarca | E9: Norte | F9: 244 | G9: 17080
B10: HP-115 | C10: Camioneta | D10: Cusco | E10: Sur | F10: 93 | G10: 6510
B11: HP-101 | C11: Automóvil | D11: Huancavelica | E11: Centro | F11: 52 | G11: 3640
B12: HP-090 | C12: Omnibus | D12: Huanuco | E12: Centro | F12: 166 | G12: 11620
B13: HP-090 | C13: Omnibus | D13: Ica | E13: Sur | F13: 180 | G13: 12600
B14: HP-115 | C14: Camioneta | D14: Junin | E14: Centro | F14: 78 | G14: 5460
B15: HP-130 | C15: Camión | D15: La Libertad | E15: Norte | F15: 146 | G15: 10220
B16: HP-130 | C16: Camión | D16: Lambayeque | E16: Norte | F16: 377 | G16: 26390
B17: HP-090 | C17: Omnibus | D17: Lima | E17: Centro | F17: 210 | G17: 14700
B18: HP-101 | C18: Automóvil | D18: Loreto | E18: Norte | F18: 109 | G18: 7630
B19: HP-101 | C19: Automóvil | D19: Madre de Dios | E19: Sur | F19: 369 | G19: 25830
B20: HP-101 | C20: Automóvil | D20: Moquegua | E20: Sur | F20: 498 | G20: 34860
... B47: HP-101 | C47: Automóvil | D47: Ucayali | E47: Norte | F47: 90 | G47: 6300

Sheet ADM_ESC
B3: Proyecto HONDA | E3: Crear 03 escenarios donde se pueda evaluar el proyecto y reflejarlo en un resumen y reporte | M3: 1 PT
E4: Para ello los escenarios deben variar en sus gastos
B5: Presupuesto Honda del Peru | C5: 20000 | E5: Procurar que en los reportes los resultados tengan nombres de rango como lo visto en clase
B6: Presupuesto Fastlane | C6: 20000
B7: Total ingresos | C7: =SUM(C5:C6) -> 40000
B9: Local- Alquiler | C9: 22000
B10: Publicidad | C10: 5000
B11: Marketing | C11: 9000
B12: Viaticos | C12: 800
B13: Transporte | C13: 900
B14: Total gastos | C14: =SUM(C9:C13) -> 37700
B16: Utilidad-Beneficio-Ahorro | C16: =C7-C14 -> 2300

Sheet Resumen del escenario
B2: Resumen del escenario
D3: Valores actuales: | E3: ESC1 | F3: ESC2 | G3: ESC3
E4: Creado por Alonso Manuel Pérez Guanilo el 12/02/2026 | F4: Creado por Alonso Manuel Pérez Guanilo el 12/02/2026 | G4: Creado por Alonso Manuel Pérez Guanilo el 12/02/2026
B5: Celdas cambiantes:
C6: Alquiler | D6: 22000 | E6: 22500 | F6: 23000 | G6: 24000
C7: Publicidad | D7: 5000 | E7: 4500 | F7: 4500 | G7: 4500
C8: Marketing | D8: 9000 | E8: 8000 | F8: 8000 | G8: 9500
C9: Viaticos | D9: 800 | E9: 900 | F9: 850 | G9: 900
C10: Transporte | D10: 900 | E10: 800 | F10: 850 | G10: 800
B11: Celdas de resultado:
C12: UTILIDAD | D12: 2300 | E12: 3300 | F12: 2800 | G12: 300
B13: Notas: La columna de valores actuales representa los valores de las celdas cambiantes
B14: en el momento en que se creó el Informe resumen de escenario. Las celdas cambiantes de
B15: cada escenario se muestran en gris.

Sheet SOLVER 
B2: Aplicar Solver para hallar el precio sea el 10000$, sabiendo que las cantidades deben ser numeros mayores que cero | G2: 0.5 pts
B5: Servidor HP DL 380p G8
B6: NRO. DE PARTE | C6: DESCRIPCION | D6: CANTIDAD | E6: PRECIO UNIT | F6: PRECIO
B7: 642106-001 | C7: HP ProLiant DL380p Gen8 High Performance | D7: 1 | E7: 7532.5 | F7: =E7*D7 -> 7532.5
B8: 652611-B21 | C8: HP 300GB 6G SAS 15K 2.5in SC ENT HDD | D8: 1 | E8: 586.5 | F8: =E8*D8 -> 586.5
B9: 647897-B21 | C9: HP 8GB 2Rx4 PC3L-10600 Registered Kit | D9: 1 | E9: 184 | F9: =E9*D9 -> 184
B10: U4506E | C10: HP Install ProLiant DL36x Service | D10: 1 | E10: 133.4 | F10: =E10*D10 -> 133.4
B11: 666988-B21 | C11: HP 2U Security Bezel Gen8 Kit | D11: 49.638095 | E11: 31.5 | F11: =E11*D11 -> 1563.6
F12: =SUM(F7:F11) -> 10000 | G12: SUMA
F15: =F12 -> 10000 | G15: TOTAL | I15: 0.5 pts
F16: 0.35 | G16: % DESCUENTO
F17: =F15*F16 -> 3500 | G17: IMPORTE DSCTO.
F18: =F15-F17 -> 6500 | G18: TOTAL FINAL

Sheet SOLVER2 
A1: El ejemplo es el siguiente. Tengo un establecimiento de venta de autos que ofrece 3 tipos de autos | M1: 1 pt
A2: Ferrari ($400000) , Lamborgini ($350000) y Porsche($300000)
A3: Se necesita ingresos sustanciales pero ellos trataran de hacer que su total de ventas sea la maxima posible
A4: Existen restricciones de venta como que los Los ferraris como maximo deben vender 100, los Lamboginis deben ser maximo 50
A5: y la venta de Porsches como maximo 35. Las cantidades son nros enteros. Por otro lado el total de ventas debe ser menor a 60millones$
A6: Establecer un cuadro de Producto / Cantidad de manera que hayemos la cantidad optima por cada autoy utilizar Solver para saber cuanto sera el Total de Ventas
A7: El cuadro debe tener su formato correspondiente en su presentacion
C13: Precio Ferrari | D13: 400000 | F13: Ferraris Máx. a vender | G13: 100
C14: Ferraris a vender | D14: 100 | F14: Lamborginis Máx. a vender | G14: 50
C15: Total Ferraris | D15: =D13*D14 -> 40000000 | F15: Porsches Máx. a vender | G15: 35
C17: Precio Lamborgini | D17: 350000
C18: Lamborginis a vender | D18: 50
C19: Total Lamborginis | D19: =D17*D18 -> 17500000
C21: Precio Porsche | D21: 300000
C22: Porsches a vender | D22: 8
C23: Total Porsches | D23: =D21*D22 -> 2400000
C25: Ventas Totales | D25: =SUM(D15,D19,D23) -> 59900000

Sheet TAB_DAT 
B1: Hallar el margen de utilidad bruta y utilidad Neta | N1: 1 PTS
B2: Una vez las formulas halladas: Crear 1 tablas de datos horizontal que refleje 10 variaciones de impuestos y por consiguientes sus utilidades netas
B4: Ventas Totales | C4: 10000
B5: Costo de Ventas | C5: 7000
B6: Utilidad Bruta | C6: =C4-C5 -> 3000
B7: Impuestos | C7: 0.18
B8: Utilidad Neta | C8: =C6-(C6*C7) -> 2460
F10: =C8 -> 2460
E11: 0.15 | F11: 2550
E12: 0.2 | F12: 2400
E13: 0.12 | F13: 2640
E14: 0.19 | F14: 2430
E15: 0.16 | F15: 2520
E16: 0.25 | F16: 2250
E17: 0.17 | F17: 2490
E18: 0.14 | F18: 2580
E19: 0.13 | F19: 2610
E20: 0.22 | F20: 2340
E22: Impuesto | F22: Utilidad Neta

Sheet MATRIZ
A1: PRACTICA MODULO AVANZADO1_2
A4: 1 | B4: Hallar utilizando una operación matricial , recuerda que es precio por cantidad y cambia el tipo de cambio para hallar en formato moneda euros | M4: 0.5 PT
B8: PRECIO UNITARIO | C8: CANTIDAD | D8: EUROS | F8: OPERACIÓN MATRICIAL
B9: 10 | C9: 20 | D9: 3.5 | F9: COSTO TOTAL
B10: 20 | C10: 30 | D10: 3.5 | F10: {=AVERAGE(B9:B15*C9:C15/D9:D15)} -> 191.14286 | G10: PROMEDIO
B11: 30 | C11: 50 | D11: 3.5
B12: 25 | C12: 41 | D12: 3.5
B13: 15 | C13: 18 | D13: 3.5
B14: 18 | C14: 41 | D14: 3.5
B15: 14 | C15: 25 | D15: 3.5
A19: 2 | B19: Funcion Indice | C19: =INDEX(B22:E32,2,3) -> 3 | D19: Expresar la 2da fila y 3era columna | I19: 0.5 PT
C20: =INDEX(B22:E32,4,4) -> 12 | D20: Expresar la 4ta fila y 4ta columna
B22: 1 | C22: 10 | D22: 9 | E22: 8
B23: 23 | C23: 2 | D23: 3 | E23: 1
B24: 4 | C24: 5 | D24: 6 | E24: 7
B25: 8 | C25: 9 | D25: 11 | E25: 12
B26: 2 | C26: 5 | D26: 4 | E26: 3
B27: 5 | C27: 8 | D27: 9 | E27: 7
B28: 2 | C28: 3 | D28: 4 | E28: 5
B29: 4 | C29: 5 | D29: 8 | E29: 2
B30: 10 | C30: 3 | D30: 2 | E30: 1
B31: 12 | C31: 54 | D31: 25 | E31: 3
B32: 7 | C32: 9 | D32: 88 | E32: 7
A35: 3 | B35: Funcion Desref | C35: POSICIONA LA FILA Y LA COLUMNA INICIAL DE EL CUADRO BASE A PARTIR DE LA CELDA AMARILLA PARA LLEVARLA AL NUMERO 1(PRIMERA FILA Y PRIMERA COLUMNA) | O35: 0.5 PT
C36: LUEGO CONSTRUYE MATRICIALMENTE TODA LA TABLA EN BASE A SU ANCHO Y ALTO Y REPRESENTALA EN EL CUADRO DE EL COSTADO
C37: SUMA LOS VALORES DE TODA LA MATRIZ
B38: 1 | C38: 10 | D38: 9 | E38: 8 | H38: {=OFFSET(E40,-2,-3,11,4)} -> 1 | I38: 10 | J38: 9 | K38: 8 | M38: SUMA | N38: =SUM(OFFSET(E40,-2,-3,11,4)) -> 416
B39: 23 | C39: 2 | D39: 3 | E39: 1 | H39: 23 | I39: 2 | J39: 3 | K39: 1
B40: 4 | C40: 5 | D40: 6 | E40: 7 | H40: 4 | I40: 5 | J40: 6 | K40: 7
B41: 8 | C41: 9 | D41: 11 | E41: 12 | H41: 8 | I41: 9 | J41: 11 | K41: 12
B42: 2 | C42: 5 | D42: 4 | E42: 3 | H42: 2 | I42: 5 | J42: 4 | K42: 3
B43: 5 | C43: 8 | D43: 9 | E43: 7 | H43: 5 | I43: 8 | J43: 9 | K43: 7
B44: 2 | C44: 3 | D44: 4 | E44: 5 | H44: 2 | I44: 3 | J44: 4 | K44: 5
B45: 4 | C45: 5 | D45: 8 | E45: 2 | H45: 4 | I45: 5 | J45: 8 | K45: 2
B46: 10 | C46: 3 | D46: 2 | E46: 1 | H46: 10 | I46: 3 | J46: 2 | K46: 1
B47: 12 | C47: 54 | D47: 25 | E47: 3 | H47: 12 | I47: 54 | J47: 25 | K47: 3
B48: 7 | C48: 9 | D48: 88 | E48: 7 | H48: 7 | I48: 9 | J48: 88 | K48: 7

Sheet ESTAD
A3: 1 | B3: CREAR UN RESUMEN ESTADISTICO CON ESTOS DATOS DE VENTAS ANUALES | L3: 0.5 PT
A4: 2 | B4: CREAR UN HISTOGRAMA UTILIZANDO LOS DATOS DE VENTAS ANUALES Y LAS CLASES PROPUESTAS EN EL CUADRO DEL COSTADO | L4: 0.5 PT
B8: VENTAS ANUALES | D8: CLASE | F8: VENTAS ANUALES | I8: CLASE | J8: Frecuencia | K8: % acumulado | L8: CLASE | M8: Frecuencia | N8: % acumulado
B9: 200 | D9: 100 | I9: 100 | J9: 1 | K9: 0.05 | L9: 200 | M9: 7 | N9: 0.35
B10: 300 | D10: 200 | F10: Media | G10: 248.5 | I10: 200 | J10: 7 | K10: 0.4 | L10: 300 | M10: 7 | N10: 0.7
B11: 200 | D11: 300 | F11: Error típico | G11: 20.186955 | I11: 300 | J11: 7 | K11: 0.75 | L11: 400 | M11: 5 | N11: 0.95
B12: 350 | D12: 400 | F12: Mediana | G12: 250 | I12: 400 | J12: 5 | K12: 1 | L12: 100 | M12: 1 | N12: 1
B13: 100 | F13: Moda | G13: 200 | I13: y mayor... | J13: 0 | K13: 1 | L13: y mayor... | M13: 0 | N13: 1
B14: 150 | F14: Desviación estándar | G14: 90.278808
B15: 130 | F15: Varianza de la muestra | G15: 8150.2632
B16: 250 | F16: Curtosis | G16: -1.0207831
B17: 250 | F17: Coeficiente de asimetría | G17: 0.14241766
B18: 150 | F18: Rango | G18: 300
B19: 150 | F19: Mínimo | G19: 100
B20: 250 | F20: Máximo | G20: 400
B21: 300 | F21: Suma | G21: 4970
B22: 400 | F22: Cuenta | G22: 20
B23: 350 | F23: Mayor (2) | G23: 400
B24: 330 | F24: Menor(2) | G24: 130
B25: 210 | F25: Nivel de confianza(95.0%) | G25: 42.251783
B26: 200
B27: 400
B28: 300

Sheet PRONO_TEND
B8: AÑO | C8: PBI | E8: 1 | F8: HALLAR EL PRONOSTICO DEL PBI PARA EL AÑO 2050 | K8: 0.5 PT
B9: 2015 | C9: 25343 | E9: 2050 | F9: =_xlfn.FORECAST.LINEAR(E9,C9:C15,B9:B15) -> 171759.43
B10: 2016 | C10: 32543
B11: 2017 | C11: 52343
B12: 2018 | C12: 53454
B13: 2019 | C13: 63234
B14: 2020 | C14: 34323 | E14: 2 | F14: UTILIZAR LA FUNCION JERARQUIA PARA DECIRME EN QUE PUESTA ESTA EL MONTO PBI DEL AÑO 2018 DE FORMA ASCENDENTE | P14: 0.5 PT
B15: 2021 | C15: 57348 | F15: =_xlfn.RANK.EQ(C12,C9:C15,1) -> 5
B19: 3 | C19: CREAR UN GRAFICO DE DISPERCION QUE TOME LOS VALORES DEL AÑO 2015 AL 2020 MOSTRANDO SU FORMULA DE TENDENCIA LINEAL Y EXPRESANDOLA EN EL GRAFICO | P19: 0.5 PT
C20: TAMBIEN QUE REFLEJE SU R CUADRADO
D23: R^2 | E23: =RSQ(C9:C14,B9:B14) -> 0.24747923 | O23: NOTA | P23: 18.5
O24: P.ADD | P24: 1.5
O25: TOTAL | P25: =SUM(P23:P24) -> 20
N28: NOMBRES | O28: SEMANA 1 | P28: P.ADD | Q28: SEMANA 2 | R28: P.ADD2 | S28: SEMANA 3 | T28: P.ADD3 | U28: PROMEDIO | V28: PROMEDIO FINAL
N29: Alonso Manuel Pérez Guanilo | O29: 19 | P29: 1 | Q29: 18.5 | R29: 1.5 | S29: 18.5 | T29: 1.5 | U29: 20 | V29: 20
